<?xml version="1.0" encoding="UTF-8"?>
<!DOCTYPE mapper PUBLIC "-//mybatis.org//DTD Mapper 3.0//EN" "http://mybatis.org/dtd/mybatis-3-mapper.dtd">
<mapper namespace="com.datafusion.manager.asset2.dao.MenuTmpMapper">

    <!-- 清空临时表 -->
    <delete id="truncateTable">
        TRUNCATE TABLE asset_lineage_menu_tmp
    </delete>

    <!-- 同步菜单数据到临时表 -->
    <insert id="syncMenuFromDb">
        INSERT INTO asset_lineage_menu_tmp (id, name, parent_id, component_url, component_type, app_id, app_code, app_name, order_idx)
        SELECT pi.id,
               pi.name,
               pi.parent_id,
               pi.component_url,
               pi.component_type,
               ai.id,
               ai.code,
               ai.name,
               pi.order_idx
        FROM manager.application_info ai
                 JOIN manager.permission_info pi ON ai.id = pi.app_id
    </insert>

    <!-- 查询应用名称列表 -->
    <select id="getAppNameList" resultType="com.datafusion.manager.asset2.dto.response.AppResp">
        SELECT DISTINCT app_name, app_code
        FROM asset_lineage_menu_tmp
        ORDER BY app_name
    </select>

    <!-- 根据应用名称查询菜单列表（用于构建树） -->
    <select id="getMenuTreeByAppCode" resultType="com.datafusion.manager.asset2.po.MenuEntity">
        SELECT id,
               name,
               parent_id,
               component_url,
               component_type,
               app_id,
               app_code,
               app_name
        FROM asset_lineage_menu_tmp
        WHERE app_code = #{appCode}
        ORDER BY parent_id, order_idx
    </select>

    <!-- 根据component_url批量查询菜单 -->
    <select id="selectMenusByComponentUrls" resultType="com.datafusion.manager.asset2.po.MenuEntity">
        SELECT id, name, parent_id, component_url, component_type, app_id, app_code, app_name
        FROM asset_lineage_menu_tmp
        WHERE component_url IN
        <foreach collection="componentUrls" item="url" open="(" separator="," close=")">
            #{url}
        </foreach>
    </select>

    <!-- 根据app_code和component_url批量查询菜单 -->
    <select id="selectMenusByAppCodeAndUrls" resultType="com.datafusion.manager.asset2.po.MenuEntity">
        SELECT id, name, parent_id, component_url, component_type, app_id, app_code, app_name
        FROM asset_lineage_menu_tmp
        WHERE app_code = #{appCode}
        AND component_url IN
        <foreach collection="componentUrls" item="url" open="(" separator="," close=")">
            #{url}
        </foreach>
    </select>

    <!-- 插入未匹配的菜单记录 -->
    <insert id="insertUnmatchedMenu">
        INSERT INTO asset_lineage_unmatched_menu (id, project_code, we_location, api_resource_id, creator, create_time, updater, update_time)
        VALUES (#{id}, #{projectCode}, #{weLocation}, #{apiResourceId}, #{creator}, #{createTime}, #{updater}, #{updateTime})
    </insert>

</mapper>